{
  "rank": [
    { "type": "Raw", "name": "末端" },
    { "type": "Middle", "name": "中間" },
    { "type": "End", "name": "完成" }
  ],
  "category": [
    { "type": "Battle", "name": "戦闘" },
    { "type": "NoBattle", "name": "非戦闘" },
    { "type": "Fashion", "name": "おしゃれ" },
    { "type": "Furniture", "name": "家具" },
    { "type": "GardenTools", "name": "庭具" },
    { "type": "Quest", "name": "クエスト" },
    { "type": "Other", "name": "その他" }
  ],
  "job": [
    { "type": "Carpenter", "name": "木工" },
    { "type": "Blacksmith", "name": "鍛冶" },
    { "type": "Armorer", "name": "甲冑" },
    { "type": "Goldsmith", "name": "彫金" },
    { "type": "Leatherworker", "name": "革細工" },
    { "type": "Weaver", "name": "裁縫" },
    { "type": "Alchemist", "name": "錬金" },
    { "type": "Culinarian", "name": "調理" }
  ],
  "other": [
    { "type": "default", "name": "標準" },
    { "type": "Master", "name": "秘伝書" },
    { "type": "Ishgard", "name": "イシュガルド復興" }
  ]
}
